scrapy_random_fake_ua/__init__.py
scrapy_random_fake_ua/middleware.py
scrapy_random_fake_ua-0.0.7.dist-info/LICENSE
scrapy_random_fake_ua-0.0.7.dist-info/METADATA
scrapy_random_fake_ua-0.0.7.dist-info/WHEEL
scrapy_random_fake_ua-0.0.7.dist-info/entry_points.txt
scrapy_random_fake_ua-0.0.7.dist-info/top_level.txt
scrapy_random_fake_ua-0.0.7.dist-info/RECORD
