Metadata-Version: 2.1
Name: scrapy-random-fake-ua
Version: 0.0.7
Summary: scrapy random fake useragent.
Home-page: https://github.com/zs527523251/scrapy-random-fake-ua
Author: zhousan
Author-email: 527523251@qq.com
License: MIT
Keywords: python pi
Platform: UNKNOWN
Classifier: Operating System :: OS Independent
Classifier: Topic :: Software Development
Classifier: Programming Language :: Python :: 2.7
Classifier: Programming Language :: Python :: Implementation :: PyPy
Provides-Extra: test
